django_tortoise/__init__.py
django_tortoise/apps.py
django_tortoise/asgi.py
django_tortoise/fields.py
django_tortoise/mapping.py
django_tortoise/models.py
django_tortoise-0.0.1.dist-info/LICENSE
django_tortoise-0.0.1.dist-info/METADATA
django_tortoise-0.0.1.dist-info/WHEEL
django_tortoise-0.0.1.dist-info/top_level.txt
django_tortoise-0.0.1.dist-info/RECORD
